rtide/__init__.py
rtide/rtide.py
rtide/utils/__init__.py
rtide/utils/utils.py
test/__init__.py
test/test_rtide.py
test/utils/__init__.py
test/utils/test_utils.py
rtide-0.1.0.dist-info/LICENSE
rtide-0.1.0.dist-info/METADATA
rtide-0.1.0.dist-info/WHEEL
rtide-0.1.0.dist-info/top_level.txt
rtide-0.1.0.dist-info/RECORD
