Metadata-Version: 2.1
Name: rtide
Version: 0.1.0
Summary: RTide: A python implementation of the ML Response Framework for Tidal Analyis and Prediction
Home-page: https://github.com/thomasmonahan/RTide
Author: Thomas Monahan
Author-email: thomas.monahan@eng.ox.ac.uk
Classifier: Programming Language :: Python :: 3
Classifier: License :: OSI Approved :: MIT License
Classifier: Operating System :: OS Independent
Requires-Python: >=3.6
License-File: LICENSE
Requires-Dist: numpy
Requires-Dist: pandas
Requires-Dist: tensorflow
Requires-Dist: utide
Requires-Dist: scipy
Requires-Dist: skyfield
Requires-Dist: shap
